setup.cfg
setup.py
spittalpond/__init__.py
spittalpond/config_interface.py
spittalpond/spittalbase.py
spittalpond/spittalexposure.py
spittalpond/spittalmodel.py
spittalpond/spittalpond.py
spittalpond/spittalrun.py
spittalpond.egg-info/PKG-INFO
spittalpond.egg-info/SOURCES.txt
spittalpond.egg-info/dependency_links.txt
spittalpond.egg-info/not-zip-safe
spittalpond.egg-info/requires.txt
spittalpond.egg-info/top_level.txt