Metadata-Version: 1.0
Name: spittalpond
Version: 0.1.3
Summary: A Python interface for the OasisLMF Django webservices API.
Home-page: https://github.com/beckettsimmons/spittalpond
Author: Beckett Simmons
Author-email: beckettsimmons@hotmail.com
License: UNKNOWN
Platform: UNKNOWN
